pulsarpy/__init__.py
pulsarpy/elasticsearch_utils.py
pulsarpy/models.py
pulsarpy/utils.py
pulsarpy/scripts/__init__.py
pulsarpy/scripts/clone_crispr_modification.py
pulsarpy/scripts/get_id_from_name.py
pulsarpy/scripts/get_missing.py
pulsarpy/scripts/tab_import.py
pulsarpy-1.3.0.data/scripts/clone_crispr_modification.py
pulsarpy-1.3.0.data/scripts/get_id_from_name.py
pulsarpy-1.3.0.data/scripts/get_missing.py
pulsarpy-1.3.0.data/scripts/tab_import.py
pulsarpy-1.3.0.dist-info/LICENSE.txt
pulsarpy-1.3.0.dist-info/METADATA
pulsarpy-1.3.0.dist-info/WHEEL
pulsarpy-1.3.0.dist-info/top_level.txt
pulsarpy-1.3.0.dist-info/RECORD
